cff2pages/__init__.py
cff2pages/cff2pages.py
cff2pages/resources/css/cff2pages.css
cff2pages/resources/img/github-logo.png
cff2pages/resources/img/gitlab-logo.png
cff2pages/resources/img/orcid_16x16.webp
cff2pages/templates/html/authors_macro.html
cff2pages/templates/html/base.html
cff2pages/templates/html/citation_macro.html
cff2pages/templates/html/identifiers_macro.html
cff2pages/templates/html/keyword_macro.html
cff2pages/templates/html/reference_macro.html
cff2pages/templates/md/authors_macro.md
cff2pages/templates/md/base.md
cff2pages/templates/md/citation_macro.md
cff2pages/templates/md/identifiers_macro.md
cff2pages/templates/md/keyword_macro.md
cff2pages/templates/md/reference_macro.md
cff2pages-0.2.1.dist-info/METADATA
cff2pages-0.2.1.dist-info/WHEEL
cff2pages-0.2.1.dist-info/entry_points.txt
cff2pages-0.2.1.dist-info/licenses/LICENSE
cff2pages-0.2.1.dist-info/RECORD
