Metadata-Version: 2.4
Name: cff2pages
Version: 0.2.1
Summary: This repository generates HTML pages or Markdown sites for GitHub and GitLab based on your Citation.cff file. This ensures that your CFF is optimized for both machine processing and human readability.
Project-URL: Homepage, https://github.com/University-of-Potsdam-MM/cff2pages
Project-URL: Documentation, https://github.com/University-of-Potsdam-MM/cff2pages
Project-URL: Bug Tracker, https://github.com/University-of-Potsdam-MM/cff2pages/issues
Project-URL: Repository, https://github.com/University-of-Potsdam-MM/cff2pages/
Project-URL: Changelog, https://university-of-potsdam-mm.github.io/cff2pages/changelog.html
Author-email: Jan Bernoth <jan.bernoth@uni-potsdam.de>
Maintainer-email: Jan Bernoth <jan.bernoth@uni-potsdam.de>
License: MIT
License-File: LICENSE
Keywords: cff,citation,html,markdown,research software
Classifier: License :: OSI Approved :: MIT License
Classifier: Operating System :: OS Independent
Classifier: Programming Language :: Python :: 3
Requires-Python: >=3.11
Requires-Dist: cffconvert>=2.0.0
Requires-Dist: jinja2>=3.1.6
Provides-Extra: docs
Requires-Dist: myst-parser~=4.0.1; extra == 'docs'
Requires-Dist: sphinx-rtd-theme~=1.3.0; extra == 'docs'
Requires-Dist: sphinx~=7.2.6; extra == 'docs'
Provides-Extra: test
Requires-Dist: beautifulsoup4~=4.13.4; extra == 'test'
Requires-Dist: flake8~=7.2.0; extra == 'test'
Requires-Dist: markdown~=3.8; extra == 'test'
Requires-Dist: pytest~=8.4.0; extra == 'test'
Requires-Dist: toml~=0.10.2; extra == 'test'
